odoo9_addon_fetchmail_bydate-9.0.1.0.0.99.dev5-py2.7-nspkg.pth
odoo9_addon_fetchmail_bydate-9.0.1.0.0.99.dev5.dist-info/METADATA
odoo9_addon_fetchmail_bydate-9.0.1.0.0.99.dev5.dist-info/RECORD
odoo9_addon_fetchmail_bydate-9.0.1.0.0.99.dev5.dist-info/WHEEL
odoo9_addon_fetchmail_bydate-9.0.1.0.0.99.dev5.dist-info/namespace_packages.txt
odoo9_addon_fetchmail_bydate-9.0.1.0.0.99.dev5.dist-info/top_level.txt
odoo_addons/fetchmail_bydate/README.rst
odoo_addons/fetchmail_bydate/__init__.py
odoo_addons/fetchmail_bydate/__openerp__.py
odoo_addons/fetchmail_bydate/i18n/ca.po
odoo_addons/fetchmail_bydate/i18n/de.po
odoo_addons/fetchmail_bydate/i18n/es.po
odoo_addons/fetchmail_bydate/i18n/fetchmail_bydate.pot
odoo_addons/fetchmail_bydate/i18n/fr.po
odoo_addons/fetchmail_bydate/i18n/hr.po
odoo_addons/fetchmail_bydate/i18n/it.po
odoo_addons/fetchmail_bydate/i18n/pt_BR.po
odoo_addons/fetchmail_bydate/i18n/sl.po
odoo_addons/fetchmail_bydate/i18n/tr.po
odoo_addons/fetchmail_bydate/i18n/zh_CN.po
odoo_addons/fetchmail_bydate/models/__init__.py
odoo_addons/fetchmail_bydate/models/fetchmail.py
odoo_addons/fetchmail_bydate/static/description/icon.png
odoo_addons/fetchmail_bydate/views/fetchmail_view.xml
