Metadata-Version: 2.1
Name: odoo9-addon-fetchmail-bydate
Version: 9.0.1.0.0.99.dev5
Summary: Fetchmail by date and unseen messages
Home-page: https://github.com/OCA/server-tools/tree/9.0
Author: Innoviu, Agile Business Group, Eficent, Odoo Community Association (OCA)
Author-email: support@odoo-community.org
License: AGPL-3
Platform: UNKNOWN
Classifier: Programming Language :: Python
Classifier: Framework :: Odoo
Classifier: License :: OSI Approved :: GNU Affero General Public License v3
Requires-Python: ~=2.7
Requires-Dist: odoo (<9.1a,>=9.0a)
